kappe/__init__.py
kappe/__main__.py
kappe/cli.py
kappe/convert.py
kappe/cut.py
kappe/plugin.py
kappe/reader.py
kappe/settings.py
kappe/writer.py
kappe/module/__init__.py
kappe/module/pointcloud.py
kappe/module/qos.py
kappe/module/tf.py
kappe/module/timing.py
kappe/plugins/__init__.py
kappe/plugins/camera_info.py
kappe/plugins/image.py
kappe/utils/__init__.py
kappe/utils/json_to_mcap.py
kappe/utils/mcap_to_json.py
kappe/utils/msg_def.py
kappe/utils/settings.py
kappe-0.23.1.dist-info/METADATA
kappe-0.23.1.dist-info/WHEEL
kappe-0.23.1.dist-info/entry_points.txt
kappe-0.23.1.dist-info/licenses/LICENSE
kappe-0.23.1.dist-info/RECORD
