Metadata-Version: 2.4
Name: kappe
Version: 0.23.1
Summary: Kappe is an efficient data migration tool designed to seamlessly convert and split MCAP files.
Project-URL: repository, https://github.com/sensmore/kappe
Author: Marko Bausch
License-File: LICENSE
Classifier: Development Status :: 4 - Beta
Classifier: Intended Audience :: Developers
Classifier: License :: OSI Approved :: GNU General Public License v3 (GPLv3)
Classifier: Programming Language :: Python :: 3.10
Classifier: Programming Language :: Python :: 3.11
Classifier: Programming Language :: Python :: 3.12
Classifier: Programming Language :: Python :: 3.13
Requires-Python: >=3.10
Requires-Dist: jsonargparse[signatures]>=4.35.0
Requires-Dist: mcap-ros1-support>=0.6.0
Requires-Dist: mcap-ros2-support>=0.3.0
Requires-Dist: mcap>=1.0.2
Requires-Dist: numpy
Requires-Dist: platformdirs>=4.3.8
Requires-Dist: pointcloud2>=0.2.3
Requires-Dist: pydantic-yaml>=1.2.1
Requires-Dist: pydantic>=2.4.2
Requires-Dist: pyyaml>=6.0.1
Requires-Dist: scipy>=1.11.1
Requires-Dist: tqdm
Provides-Extra: plugin-image
Requires-Dist: pillow>=8.0.0; extra == 'plugin-image'
